prometheus_ncs2_exporter/__init__.py
prometheus_ncs2_exporter/main.py
prometheus_ncs2_exporter-0.1.0.dist-info/LICENSE
prometheus_ncs2_exporter-0.1.0.dist-info/METADATA
prometheus_ncs2_exporter-0.1.0.dist-info/WHEEL
prometheus_ncs2_exporter-0.1.0.dist-info/entry_points.txt
prometheus_ncs2_exporter-0.1.0.dist-info/top_level.txt
prometheus_ncs2_exporter-0.1.0.dist-info/RECORD
