Metadata-Version: 2.1
Name: prometheus-ncs2-exporter
Version: 0.1.0
Summary: Prometheus Exporter for Intel NCS2 Metrics
Home-page: https://github.com/adaptant-labs/prometheus_ncs2_exporter
Author: Adaptant Labs
Author-email: labs@adaptant.io
License: Apache 2.0
Keywords: prometheus,movidius,ncs2,myriad,myriadx,monitoring,exporter
Platform: UNKNOWN
Classifier: Development Status :: 3 - Alpha
Classifier: Intended Audience :: Developers
Classifier: Intended Audience :: System Administrators
Classifier: Topic :: System :: Hardware
Classifier: Topic :: System :: Monitoring
Classifier: Programming Language :: Python :: 3
Classifier: Programming Language :: Python :: 3.7
Classifier: Programming Language :: Python :: 3.8
Classifier: License :: OSI Approved :: Apache Software License
Requires-Dist: prometheus-client
Requires-Dist: pyusb
